{
  "step_100": {
    "soma": [
      {
        "feature": "AHP_depth",
        "val": [
          20.73680135311302,
          0.4882746222175169
        ],
        "n": 5
      },
      {
        "feature": "AP1_amp",
        "val": [
          75.01875599701324,
          1.3475394556193083
        ],
        "n": 5
      },
      {
        "feature": "AP2_amp",
        "val": [
          69.45117655590548,
          1.763537203598925
        ],
        "n": 4
      },
      {
        "feature": "AHP_time_from_peak",
        "val": [
          1.511666666672166,
          0.07446102634589984
        ],
        "n": 5
      },
      {
        "feature": "AP_amplitude",
        "val": [
          72.11563049258292,
          1.7239519808314223
        ],
        "n": 5
      },
      {
        "feature": "AP_duration_half_width",
        "val": [
          0.5129166666685328,
          0.10277740240209081
        ],
        "n": 5
      },
      {
        "feature": "AP_begin_width",
        "val": [
          1.1700000000042565,
          0.029154759474332565
        ],
        "n": 5
      },
      {
        "feature": "mean_frequency",
        "val": [
          3.5318749997434793,
          1.3941524437161446
        ],
        "n": 5
      },
      {
        "feature": "voltage_base",
        "val": [
          -91.7123221857072,
          0.5308377214205631
        ],
        "n": 5
      },
      {
        "feature": "inv_time_to_first_spike",
        "val": [
          2.3602686421853543,
          0.8372543961759972
        ],
        "n": 5
      },
      {
        "feature": "inv_first_ISI",
        "val": [
          6.36126358933156,
          3.2902782761845137
        ],
        "n": 5
      },
      {
        "feature": "inv_second_ISI",
        "val": [
          1.7823426834182576,
          2.270040056041589
        ],
        "n": 5
      },
      {
        "feature": "inv_third_ISI",
        "val": [
          1.072386058977332,
          2.144772117954664
        ],
        "n": 5
      },
      {
        "feature": "inv_fourth_ISI",
        "val": [
          0.0,
          0.001
        ],
        "n": 5
      },
      {
        "feature": "inv_fifth_ISI",
        "val": [
          0.0,
          0.001
        ],
        "n": 5
      },
      {
        "feature": "APlast_amp",
        "val": [
          69.67500439909192,
          2.9617759219243722
        ],
        "n": 5
      },
      {
        "feature": "AP_begin_voltage",
        "val": [
          -54.298961028525945,
          0.9185290395436478
        ],
        "n": 5
      },
      {
        "feature": "ISI_CV",
        "val": [
          0.010311576069153002,
          0.001
        ],
        "n": 1
      },
      {
        "feature": "ISI_log_slope",
        "val": [
          0.021038863853564,
          0.001
        ],
        "n": 1
      },
      {
        "feature": "fast_AHP",
        "val": [
          15.903317313540144,
          0.6471391074522853
        ],
        "n": 4
      },
      {
        "feature": "adaptation_index2",
        "val": [
          0.007291385363219011,
          0.001
        ],
        "n": 1
      },
      {
        "feature": "AHP_slow_time",
        "val": [
          0.22540410595085025,
          0.010277948891218469
        ],
        "n": 2
      },
      {
        "feature": "doublet_ISI",
        "val": [
          127.55000000046402,
          15.109682326298627
        ],
        "n": 4
      },
      {
        "feature": "decay_time_constant_after_stim",
        "val": [
          1050.9903382524308,
          533.6562551751238
        ],
        "n": 5
      },
      {
        "feature": "mean_AP_amplitude",
        "val": [
          72.11563049258292,
          1.7239519808314223
        ],
        "n": 5
      }
    ]
  },
  "step_150": {
    "soma": [
      {
        "feature": "AHP_depth",
        "val": [
          21.538668263471028,
          0.001
        ],
        "n": 1
      },
      {
        "feature": "AP1_amp",
        "val": [
          76.96875761658038,
          0.001
        ],
        "n": 1
      },
      {
        "feature": "AP2_amp",
        "val": [
          70.34374999254271,
          0.001
        ],
        "n": 1
      },
      {
        "feature": "AHP_time_from_peak",
        "val": [
          1.5416666666722751,
          0.001
        ],
        "n": 1
      },
      {
        "feature": "AP_amplitude",
        "val": [
          70.95833777653053,
          0.001
        ],
        "n": 1
      },
      {
        "feature": "AP_duration_half_width",
        "val": [
          0.5666666666687282,
          0.001
        ],
        "n": 1
      },
      {
        "feature": "AP_begin_width",
        "val": [
          1.1583333333375474,
          0.001
        ],
        "n": 1
      },
      {
        "feature": "mean_frequency",
        "val": [
          14.018691588782842,
          0.001
        ],
        "n": 1
      },
      {
        "feature": "voltage_base",
        "val": [
          -92.00741826343659,
          0.001
        ],
        "n": 1
      },
      {
        "feature": "inv_time_to_first_spike",
        "val": [
          7.782101167331975,
          0.001
        ],
        "n": 1
      },
      {
        "feature": "inv_first_ISI",
        "val": [
          25.974025973931482,
          0.001
        ],
        "n": 1
      },
      {
        "feature": "inv_second_ISI",
        "val": [
          21.276595744603448,
          0.001
        ],
        "n": 1
      },
      {
        "feature": "inv_third_ISI",
        "val": [
          0.0,
          0.001
        ],
        "n": 1
      },
      {
        "feature": "inv_fourth_ISI",
        "val": [
          0.0,
          0.001
        ],
        "n": 1
      },
      {
        "feature": "inv_fifth_ISI",
        "val": [
          0.0,
          0.001
        ],
        "n": 1
      },
      {
        "feature": "APlast_amp",
        "val": [
          65.5625057204685,
          0.001
        ],
        "n": 1
      },
      {
        "feature": "AP_begin_voltage",
        "val": [
          -52.73958587738127,
          0.001
        ],
        "n": 1
      },
      {
        "feature": "fast_AHP",
        "val": [
          17.21874809088809,
          0.001
        ],
        "n": 1
      },
      {
        "feature": "AHP_slow_time",
        "val": [
          0.10638297872340426,
          0.001
        ],
        "n": 1
      },
      {
        "feature": "doublet_ISI",
        "val": [
          38.50000000014006,
          0.001
        ],
        "n": 1
      },
      {
        "feature": "decay_time_constant_after_stim",
        "val": [
          314.5602291097864,
          0.001
        ],
        "n": 1
      },
      {
        "feature": "mean_AP_amplitude",
        "val": [
          70.95833777653053,
          0.001
        ],
        "n": 1
      }
    ]
  },
  "step_250": {
    "soma": [
      {
        "feature": "AHP_depth",
        "val": [
          20.0421285914162,
          0.001
        ],
        "n": 1
      },
      {
        "feature": "AP1_amp",
        "val": [
          77.96875372808177,
          0.001
        ],
        "n": 1
      },
      {
        "feature": "AP2_amp",
        "val": [
          68.59375190007239,
          0.001
        ],
        "n": 1
      },
      {
        "feature": "AHP_time_from_peak",
        "val": [
          1.450000000005275,
          0.001
        ],
        "n": 1
      },
      {
        "feature": "AP_amplitude",
        "val": [
          73.28125281407708,
          0.001
        ],
        "n": 1
      },
      {
        "feature": "AP_duration_half_width",
        "val": [
          0.5500000000020009,
          0.001
        ],
        "n": 1
      },
      {
        "feature": "AP_begin_width",
        "val": [
          1.1250000000040927,
          0.001
        ],
        "n": 1
      },
      {
        "feature": "mean_frequency",
        "val": [
          25.316455696349134,
          0.001
        ],
        "n": 1
      },
      {
        "feature": "voltage_base",
        "val": [
          -91.04212859058245,
          0.001
        ],
        "n": 1
      },
      {
        "feature": "inv_time_to_first_spike",
        "val": [
          16.920473773417356,
          0.001
        ],
        "n": 1
      },
      {
        "feature": "inv_first_ISI",
        "val": [
          50.25125628122422,
          0.001
        ],
        "n": 1
      },
      {
        "feature": "inv_second_ISI",
        "val": [
          0.0,
          0.001
        ],
        "n": 1
      },
      {
        "feature": "inv_third_ISI",
        "val": [
          0.0,
          0.001
        ],
        "n": 1
      },
      {
        "feature": "inv_fourth_ISI",
        "val": [
          0.0,
          0.001
        ],
        "n": 1
      },
      {
        "feature": "inv_fifth_ISI",
        "val": [
          0.0,
          0.001
        ],
        "n": 1
      },
      {
        "feature": "APlast_amp",
        "val": [
          68.59375190007239,
          0.001
        ],
        "n": 1
      },
      {
        "feature": "AP_begin_voltage",
        "val": [
          -54.687501910709,
          0.001
        ],
        "n": 1
      },
      {
        "feature": "fast_AHP",
        "val": [
          15.093746181493799,
          0.001
        ],
        "n": 1
      },
      {
        "feature": "doublet_ISI",
        "val": [
          19.900000000072396,
          0.001
        ],
        "n": 1
      },
      {
        "feature": "decay_time_constant_after_stim",
        "val": [
          514.2654092225303,
          0.001
        ],
        "n": 1
      },
      {
        "feature": "mean_AP_amplitude",
        "val": [
          73.28125281407708,
          0.001
        ],
        "n": 1
      }
    ]
  },
  "step_300": {
    "soma": [
      {
        "feature": "AHP_depth",
        "val": [
          21.112472596454584,
          0.5191311832458058
        ],
        "n": 3
      },
      {
        "feature": "AP1_amp",
        "val": [
          77.6406265501088,
          0.3444610669826976
        ],
        "n": 3
      },
      {
        "feature": "AP2_amp",
        "val": [
          67.5833358584558,
          0.4789425360112799
        ],
        "n": 3
      },
      {
        "feature": "AHP_time_from_peak",
        "val": [
          1.4916666666720932,
          0.01800205749564294
        ],
        "n": 3
      },
      {
        "feature": "AP_amplitude",
        "val": [
          68.60243233455851,
          0.5328861030932937
        ],
        "n": 3
      },
      {
        "feature": "AP_duration_half_width",
        "val": [
          0.569444444446516,
          0.007856742013212462
        ],
        "n": 3
      },
      {
        "feature": "AP_begin_width",
        "val": [
          1.1750000000042746,
          0.006804138174422531
        ],
        "n": 3
      },
      {
        "feature": "mean_frequency",
        "val": [
          35.910897869841754,
          0.643870222734346
        ],
        "n": 3
      },
      {
        "feature": "voltage_base",
        "val": [
          -91.40413926251692,
          0.4758756871762417
        ],
        "n": 3
      },
      {
        "feature": "inv_time_to_first_spike",
        "val": [
          20.000396418015224,
          0.5191138220570167
        ],
        "n": 3
      },
      {
        "feature": "inv_first_ISI",
        "val": [
          68.74817624719664,
          2.633662215178748
        ],
        "n": 3
      },
      {
        "feature": "inv_second_ISI",
        "val": [
          53.31593824725113,
          5.412080603973889
        ],
        "n": 3
      },
      {
        "feature": "inv_third_ISI",
        "val": [
          0.0,
          0.001
        ],
        "n": 3
      },
      {
        "feature": "inv_fourth_ISI",
        "val": [
          0.0,
          0.001
        ],
        "n": 3
      },
      {
        "feature": "inv_fifth_ISI",
        "val": [
          0.0,
          0.001
        ],
        "n": 3
      },
      {
        "feature": "APlast_amp",
        "val": [
          60.583334595110934,
          2.336494059700325
        ],
        "n": 3
      },
      {
        "feature": "AP_begin_voltage",
        "val": [
          -53.60590373558919,
          0.3795137480507569
        ],
        "n": 3
      },
      {
        "feature": "fast_AHP",
        "val": [
          15.846353366869842,
          0.2912253577385292
        ],
        "n": 3
      },
      {
        "feature": "AHP_slow_time",
        "val": [
          0.26657969123722547,
          0.027060403019967896
        ],
        "n": 3
      },
      {
        "feature": "doublet_ISI",
        "val": [
          14.56666666671966,
          0.5436502143453141
        ],
        "n": 3
      },
      {
        "feature": "decay_time_constant_after_stim",
        "val": [
          657.5443462367093,
          248.738052738659
        ],
        "n": 3
      },
      {
        "feature": "mean_AP_amplitude",
        "val": [
          68.60243233455851,
          0.5328861030932937
        ],
        "n": 3
      }
    ]
  }
}