{
  "step_80": {
    "soma": [
      {
        "feature": "voltage_base",
        "val": [
          -87.55712448882865,
          0.001
        ],
        "n": 1
      },
      {
        "feature": "inv_time_to_first_spike",
        "val": [
          0.0,
          0.001
        ],
        "n": 1
      },
      {
        "feature": "inv_first_ISI",
        "val": [
          0.0,
          0.001
        ],
        "n": 1
      },
      {
        "feature": "inv_second_ISI",
        "val": [
          0.0,
          0.001
        ],
        "n": 1
      },
      {
        "feature": "inv_third_ISI",
        "val": [
          0.0,
          0.001
        ],
        "n": 1
      },
      {
        "feature": "inv_fourth_ISI",
        "val": [
          0.0,
          0.001
        ],
        "n": 1
      },
      {
        "feature": "inv_fifth_ISI",
        "val": [
          0.0,
          0.001
        ],
        "n": 1
      },
      {
        "feature": "decay_time_constant_after_stim",
        "val": [
          1033.3174952504578,
          0.001
        ],
        "n": 1
      }
    ]
  },
  "step_100": {
    "soma": [
      {
        "feature": "AHP_depth",
        "val": [
          26.79931399967569,
          0.39450658500500757
        ],
        "n": 7
      },
      {
        "feature": "AP1_amp",
        "val": [
          82.1406286512356,
          2.074621329337124
        ],
        "n": 7
      },
      {
        "feature": "AP2_amp",
        "val": [
          78.70625372895908,
          1.1717064188177206
        ],
        "n": 5
      },
      {
        "feature": "AHP_time_from_peak",
        "val": [
          1.776398809530272,
          0.06484363004752544
        ],
        "n": 7
      },
      {
        "feature": "AP_amplitude",
        "val": [
          79.05019927014091,
          1.3518088205963974
        ],
        "n": 7
      },
      {
        "feature": "AP_duration_half_width",
        "val": [
          0.5940773809545422,
          0.015737435599661804
        ],
        "n": 7
      },
      {
        "feature": "AP_begin_width",
        "val": [
          1.3445238095287009,
          0.0358204770483735
        ],
        "n": 7
      },
      {
        "feature": "mean_frequency",
        "val": [
          4.389793013619246,
          2.1375669573693563
        ],
        "n": 7
      },
      {
        "feature": "burst_number",
        "val": [
          1.0,
          0.001
        ],
        "n": 2
      },
      {
        "feature": "voltage_base",
        "val": [
          -87.45599829122779,
          0.39267722902845337
        ],
        "n": 9
      },
      {
        "feature": "inv_time_to_first_spike",
        "val": [
          4.5484322803499895,
          3.6565553275076597
        ],
        "n": 9
      },
      {
        "feature": "inv_first_ISI",
        "val": [
          4.097694145808386,
          6.21684921269639
        ],
        "n": 9
      },
      {
        "feature": "inv_second_ISI",
        "val": [
          2.774913177059187,
          3.190205114462059
        ],
        "n": 9
      },
      {
        "feature": "inv_third_ISI",
        "val": [
          1.3217150245393712,
          2.5231453007976734
        ],
        "n": 9
      },
      {
        "feature": "inv_fourth_ISI",
        "val": [
          1.38776367509322,
          2.6932101705750497
        ],
        "n": 9
      },
      {
        "feature": "inv_fifth_ISI",
        "val": [
          0.8373105584830963,
          2.3682718954499706
        ],
        "n": 9
      },
      {
        "feature": "APlast_amp",
        "val": [
          77.80692385442323,
          2.225736590565639
        ],
        "n": 7
      },
      {
        "feature": "AP_begin_voltage",
        "val": [
          -57.73057012833244,
          8.423611280791668
        ],
        "n": 7
      },
      {
        "feature": "ISI_CV",
        "val": [
          0.09443640600650864,
          0.022293879333891667
        ],
        "n": 2
      },
      {
        "feature": "ISI_log_slope",
        "val": [
          0.1133256234224655,
          0.01735615953461675
        ],
        "n": 2
      },
      {
        "feature": "fast_AHP",
        "val": [
          8.966472163227463,
          1.4996914207347292
        ],
        "n": 7
      },
      {
        "feature": "adaptation_index2",
        "val": [
          0.027086559053296964,
          0.007963153441886982
        ],
        "n": 2
      },
      {
        "feature": "AHP_slow_time",
        "val": [
          0.1807097612085648,
          0.0626945759587755
        ],
        "n": 5
      },
      {
        "feature": "doublet_ISI",
        "val": [
          219.18000000079738,
          101.94424750850641
        ],
        "n": 5
      },
      {
        "feature": "decay_time_constant_after_stim",
        "val": [
          854.5240912200154,
          647.0430429246268
        ],
        "n": 9
      },
      {
        "feature": "mean_AP_amplitude",
        "val": [
          79.05019927014091,
          1.3518088205964018
        ],
        "n": 7
      }
    ]
  },
  "step_125": {
    "soma": [
      {
        "feature": "AHP_depth",
        "val": [
          26.709998498551528,
          0.19901916738217795
        ],
        "n": 4
      },
      {
        "feature": "AP1_amp",
        "val": [
          81.6054732597916,
          0.5761546324559976
        ],
        "n": 4
      },
      {
        "feature": "AP2_amp",
        "val": [
          78.17708579300655,
          0.7026440712303788
        ],
        "n": 3
      },
      {
        "feature": "AHP_time_from_peak",
        "val": [
          1.780833333339812,
          0.02657536453193334
        ],
        "n": 4
      },
      {
        "feature": "AP_amplitude",
        "val": [
          79.46732138118816,
          0.8203341332959523
        ],
        "n": 4
      },
      {
        "feature": "AP_duration_half_width",
        "val": [
          0.6029166666688601,
          0.013090231727051791
        ],
        "n": 4
      },
      {
        "feature": "AP_begin_width",
        "val": [
          1.3695833333383158,
          0.026441103313771353
        ],
        "n": 4
      },
      {
        "feature": "mean_frequency",
        "val": [
          4.003396206679001,
          0.9720641580437256
        ],
        "n": 4
      },
      {
        "feature": "burst_number",
        "val": [
          1.0,
          0.001
        ],
        "n": 1
      },
      {
        "feature": "voltage_base",
        "val": [
          -87.29854296231277,
          0.14291334501743494
        ],
        "n": 4
      },
      {
        "feature": "inv_time_to_first_spike",
        "val": [
          5.373794965168124,
          1.8294814464787608
        ],
        "n": 4
      },
      {
        "feature": "inv_first_ISI",
        "val": [
          3.333593473770124,
          2.015523401964821
        ],
        "n": 4
      },
      {
        "feature": "inv_second_ISI",
        "val": [
          2.851578801733638,
          1.9273185547531193
        ],
        "n": 4
      },
      {
        "feature": "inv_third_ISI",
        "val": [
          1.220703124995559,
          2.11431983345041
        ],
        "n": 4
      },
      {
        "feature": "inv_fourth_ISI",
        "val": [
          1.1814744801469306,
          2.0463738274605103
        ],
        "n": 4
      },
      {
        "feature": "inv_fifth_ISI",
        "val": [
          0.0,
          0.001
        ],
        "n": 4
      },
      {
        "feature": "APlast_amp",
        "val": [
          78.24804961574972,
          1.5508802212546442
        ],
        "n": 4
      },
      {
        "feature": "AP_begin_voltage",
        "val": [
          -58.75787975781485,
          7.564716409631956
        ],
        "n": 4
      },
      {
        "feature": "ISI_CV",
        "val": [
          0.07214252667261697,
          0.001
        ],
        "n": 1
      },
      {
        "feature": "ISI_log_slope",
        "val": [
          0.13068178295708224,
          0.001
        ],
        "n": 1
      },
      {
        "feature": "fast_AHP",
        "val": [
          8.149089124039524,
          0.8222513461427509
        ],
        "n": 4
      },
      {
        "feature": "adaptation_index2",
        "val": [
          0.035049712495183946,
          0.001
        ],
        "n": 1
      },
      {
        "feature": "AHP_slow_time",
        "val": [
          0.19297945061499341,
          0.07809937519707597
        ],
        "n": 3
      },
      {
        "feature": "doublet_ISI",
        "val": [
          230.1000000008371,
          32.99737363298159
        ],
        "n": 3
      },
      {
        "feature": "decay_time_constant_after_stim",
        "val": [
          689.910993260467,
          298.4924941665936
        ],
        "n": 4
      },
      {
        "feature": "mean_AP_amplitude",
        "val": [
          79.46732138118816,
          0.8203341332959523
        ],
        "n": 4
      }
    ]
  },
  "step_175": {
    "soma": [
      {
        "feature": "AHP_depth",
        "val": [
          30.370617148992423,
          0.001
        ],
        "n": 1
      },
      {
        "feature": "AP1_amp",
        "val": [
          87.10937785690959,
          0.001
        ],
        "n": 1
      },
      {
        "feature": "AP2_amp",
        "val": [
          70.78125381785321,
          0.001
        ],
        "n": 1
      },
      {
        "feature": "AHP_time_from_peak",
        "val": [
          2.148275862076781,
          0.001
        ],
        "n": 1
      },
      {
        "feature": "AP_amplitude",
        "val": [
          66.24649969321365,
          0.001
        ],
        "n": 1
      },
      {
        "feature": "AP_duration_half_width",
        "val": [
          0.5965517241401013,
          0.001
        ],
        "n": 1
      },
      {
        "feature": "AP_begin_width",
        "val": [
          1.4525862069018363,
          0.001
        ],
        "n": 1
      },
      {
        "feature": "mean_frequency",
        "val": [
          29.847673939807258,
          0.001
        ],
        "n": 1
      },
      {
        "feature": "burst_number",
        "val": [
          1.0,
          0.001
        ],
        "n": 1
      },
      {
        "feature": "voltage_base",
        "val": [
          -89.08721408081085,
          0.001
        ],
        "n": 1
      },
      {
        "feature": "inv_time_to_first_spike",
        "val": [
          25.252525252908384,
          0.001
        ],
        "n": 1
      },
      {
        "feature": "inv_first_ISI",
        "val": [
          86.95652173881409,
          0.001
        ],
        "n": 1
      },
      {
        "feature": "inv_second_ISI",
        "val": [
          43.668122270583495,
          0.001
        ],
        "n": 1
      },
      {
        "feature": "inv_third_ISI",
        "val": [
          34.01360544205313,
          0.001
        ],
        "n": 1
      },
      {
        "feature": "inv_fourth_ISI",
        "val": [
          34.01360544205313,
          0.001
        ],
        "n": 1
      },
      {
        "feature": "inv_fifth_ISI",
        "val": [
          34.01360544205313,
          0.001
        ],
        "n": 1
      },
      {
        "feature": "APlast_amp",
        "val": [
          62.71875366302613,
          0.001
        ],
        "n": 1
      },
      {
        "feature": "AP_begin_voltage",
        "val": [
          -45.660156674325734,
          0.001
        ],
        "n": 1
      },
      {
        "feature": "ISI_CV",
        "val": [
          0.12396756241164719,
          0.001
        ],
        "n": 1
      },
      {
        "feature": "ISI_log_slope",
        "val": [
          0.10532002338855415,
          0.001
        ],
        "n": 1
      },
      {
        "feature": "fast_AHP",
        "val": [
          13.026133128937271,
          0.001
        ],
        "n": 1
      },
      {
        "feature": "adaptation_index2",
        "val": [
          0.008999304926338287,
          0.001
        ],
        "n": 1
      },
      {
        "feature": "AHP_slow_time",
        "val": [
          0.20577891144939767,
          0.001
        ],
        "n": 1
      },
      {
        "feature": "doublet_ISI",
        "val": [
          11.500000000041837,
          0.001
        ],
        "n": 1
      },
      {
        "feature": "decay_time_constant_after_stim",
        "val": [
          61.73387497573175,
          0.001
        ],
        "n": 1
      },
      {
        "feature": "mean_AP_amplitude",
        "val": [
          66.24649969321365,
          0.001
        ],
        "n": 1
      }
    ]
  },
  "step_200": {
    "soma": [
      {
        "feature": "AHP_depth",
        "val": [
          30.93729078534649,
          1.3398780749047874
        ],
        "n": 6
      },
      {
        "feature": "AP1_amp",
        "val": [
          84.5455766678496,
          1.8215708910721713
        ],
        "n": 6
      },
      {
        "feature": "AP2_amp",
        "val": [
          70.00260779523602,
          1.2007358562663588
        ],
        "n": 6
      },
      {
        "feature": "AHP_time_from_peak",
        "val": [
          2.291788172324527,
          0.08393823484746263
        ],
        "n": 6
      },
      {
        "feature": "AP_amplitude",
        "val": [
          63.68363976779768,
          1.6155526192869907
        ],
        "n": 6
      },
      {
        "feature": "AP_duration_half_width",
        "val": [
          0.5911718047299899,
          0.03537155898336861
        ],
        "n": 6
      },
      {
        "feature": "AP_begin_width",
        "val": [
          1.5041002125324086,
          0.030015675159782776
        ],
        "n": 6
      },
      {
        "feature": "mean_frequency",
        "val": [
          26.93014221406472,
          4.607370100552657
        ],
        "n": 6
      },
      {
        "feature": "burst_number",
        "val": [
          1.1666666666666667,
          0.3726779962499649
        ],
        "n": 6
      },
      {
        "feature": "voltage_base",
        "val": [
          -87.55965557177858,
          0.864906881983914
        ],
        "n": 6
      },
      {
        "feature": "inv_time_to_first_spike",
        "val": [
          24.673362755455486,
          1.9149297393904445
        ],
        "n": 6
      },
      {
        "feature": "inv_first_ISI",
        "val": [
          80.29750944774106,
          18.234454239954804
        ],
        "n": 6
      },
      {
        "feature": "inv_second_ISI",
        "val": [
          42.16016027064971,
          5.010539186570366
        ],
        "n": 6
      },
      {
        "feature": "inv_third_ISI",
        "val": [
          32.89974846527778,
          5.997946711193932
        ],
        "n": 6
      },
      {
        "feature": "inv_fourth_ISI",
        "val": [
          30.10536252377401,
          7.314014593816238
        ],
        "n": 6
      },
      {
        "feature": "inv_fifth_ISI",
        "val": [
          28.53472361118085,
          6.10135067946878
        ],
        "n": 6
      },
      {
        "feature": "APlast_amp",
        "val": [
          60.35547085627391,
          1.4845519434236467
        ],
        "n": 6
      },
      {
        "feature": "AP_begin_voltage",
        "val": [
          -45.500465411827996,
          0.7840443673864362
        ],
        "n": 6
      },
      {
        "feature": "ISI_CV",
        "val": [
          0.18056611172206924,
          0.09143908452914287
        ],
        "n": 6
      },
      {
        "feature": "ISI_log_slope",
        "val": [
          0.11577401613975542,
          0.011951657317004094
        ],
        "n": 6
      },
      {
        "feature": "fast_AHP",
        "val": [
          11.13722071912776,
          0.9508357904651673
        ],
        "n": 6
      },
      {
        "feature": "adaptation_index2",
        "val": [
          0.010869467806727024,
          0.0026982556716531555
        ],
        "n": 6
      },
      {
        "feature": "AHP_slow_time",
        "val": [
          0.23467384106864522,
          0.019237755801035882
        ],
        "n": 6
      },
      {
        "feature": "doublet_ISI",
        "val": [
          13.21666666671475,
          3.4820571825158817
        ],
        "n": 6
      },
      {
        "feature": "decay_time_constant_after_stim",
        "val": [
          170.7238556894778,
          133.41221699220017
        ],
        "n": 6
      },
      {
        "feature": "mean_AP_amplitude",
        "val": [
          63.68363976779768,
          1.6155526192869902
        ],
        "n": 6
      }
    ]
  },
  "step_225": {
    "soma": [
      {
        "feature": "AHP_depth",
        "val": [
          33.8453294180539,
          0.001
        ],
        "n": 1
      },
      {
        "feature": "AP1_amp",
        "val": [
          85.53125369810473,
          0.001
        ],
        "n": 1
      },
      {
        "feature": "AP2_amp",
        "val": [
          68.65625376357605,
          0.001
        ],
        "n": 1
      },
      {
        "feature": "AHP_time_from_peak",
        "val": [
          2.297142857151214,
          0.001
        ],
        "n": 1
      },
      {
        "feature": "AP_amplitude",
        "val": [
          60.96518029227621,
          0.001
        ],
        "n": 1
      },
      {
        "feature": "AP_duration_half_width",
        "val": [
          0.5971428571450296,
          0.001
        ],
        "n": 1
      },
      {
        "feature": "AP_begin_width",
        "val": [
          1.5028571428626103,
          0.001
        ],
        "n": 1
      },
      {
        "feature": "mean_frequency",
        "val": [
          35.681516974104646,
          0.001
        ],
        "n": 1
      },
      {
        "feature": "burst_number",
        "val": [
          1.0,
          0.001
        ],
        "n": 1
      },
      {
        "feature": "voltage_base",
        "val": [
          -88.38908154296821,
          0.001
        ],
        "n": 1
      },
      {
        "feature": "inv_time_to_first_spike",
        "val": [
          28.169014084995617,
          0.001
        ],
        "n": 1
      },
      {
        "feature": "inv_first_ISI",
        "val": [
          108.69565217351762,
          0.001
        ],
        "n": 1
      },
      {
        "feature": "inv_second_ISI",
        "val": [
          51.02040816307969,
          0.001
        ],
        "n": 1
      },
      {
        "feature": "inv_third_ISI",
        "val": [
          44.843049327191125,
          0.001
        ],
        "n": 1
      },
      {
        "feature": "inv_fourth_ISI",
        "val": [
          44.44444444428276,
          0.001
        ],
        "n": 1
      },
      {
        "feature": "inv_fifth_ISI",
        "val": [
          39.37007874001425,
          0.001
        ],
        "n": 1
      },
      {
        "feature": "APlast_amp",
        "val": [
          58.07031433590175,
          0.001
        ],
        "n": 1
      },
      {
        "feature": "AP_begin_voltage",
        "val": [
          -43.87934044635702,
          0.001
        ],
        "n": 1
      },
      {
        "feature": "ISI_CV",
        "val": [
          0.12564904143320954,
          0.001
        ],
        "n": 1
      },
      {
        "feature": "ISI_log_slope",
        "val": [
          0.1003300383409396,
          0.001
        ],
        "n": 1
      },
      {
        "feature": "fast_AHP",
        "val": [
          10.599109093535274,
          0.001
        ],
        "n": 1
      },
      {
        "feature": "adaptation_index2",
        "val": [
          0.00596950303970473,
          0.001
        ],
        "n": 1
      },
      {
        "feature": "AHP_slow_time",
        "val": [
          0.21434967765147084,
          0.001
        ],
        "n": 1
      },
      {
        "feature": "doublet_ISI",
        "val": [
          9.20000000003347,
          0.001
        ],
        "n": 1
      },
      {
        "feature": "decay_time_constant_after_stim",
        "val": [
          79.19964380751146,
          0.001
        ],
        "n": 1
      },
      {
        "feature": "mean_AP_amplitude",
        "val": [
          60.96518029227621,
          0.001
        ],
        "n": 1
      }
    ]
  },
  "step_300": {
    "soma": [
      {
        "feature": "AHP_depth",
        "val": [
          35.17599552044424,
          0.001
        ],
        "n": 1
      },
      {
        "feature": "AP1_amp",
        "val": [
          87.90625282623813,
          0.001
        ],
        "n": 1
      },
      {
        "feature": "AP2_amp",
        "val": [
          68.87499995976725,
          0.001
        ],
        "n": 1
      },
      {
        "feature": "AHP_time_from_peak",
        "val": [
          2.327127659582934,
          0.001
        ],
        "n": 1
      },
      {
        "feature": "AP_amplitude",
        "val": [
          54.46043986068541,
          0.001
        ],
        "n": 1
      },
      {
        "feature": "AP_duration_half_width",
        "val": [
          0.646276595747032,
          0.001
        ],
        "n": 1
      },
      {
        "feature": "AP_begin_width",
        "val": [
          1.6202127659633412,
          0.001
        ],
        "n": 1
      },
      {
        "feature": "mean_frequency",
        "val": [
          47.39336492877313,
          0.001
        ],
        "n": 1
      },
      {
        "feature": "burst_number",
        "val": [
          1.0,
          0.001
        ],
        "n": 1
      },
      {
        "feature": "voltage_base",
        "val": [
          -89.15272627258334,
          0.001
        ],
        "n": 1
      },
      {
        "feature": "inv_time_to_first_spike",
        "val": [
          33.55704698058248,
          0.001
        ],
        "n": 1
      },
      {
        "feature": "inv_first_ISI",
        "val": [
          156.24999999943157,
          0.001
        ],
        "n": 1
      },
      {
        "feature": "inv_second_ISI",
        "val": [
          86.20689655141052,
          0.001
        ],
        "n": 1
      },
      {
        "feature": "inv_third_ISI",
        "val": [
          73.52941176443838,
          0.001
        ],
        "n": 1
      },
      {
        "feature": "inv_fourth_ISI",
        "val": [
          66.66666666642413,
          0.001
        ],
        "n": 1
      },
      {
        "feature": "inv_fifth_ISI",
        "val": [
          54.94505494485506,
          0.001
        ],
        "n": 1
      },
      {
        "feature": "APlast_amp",
        "val": [
          51.124999854238396,
          0.001
        ],
        "n": 1
      },
      {
        "feature": "AP_begin_voltage",
        "val": [
          -42.182617310949354,
          0.001
        ],
        "n": 1
      },
      {
        "feature": "ISI_CV",
        "val": [
          0.12578344041971384,
          0.001
        ],
        "n": 1
      },
      {
        "feature": "ISI_log_slope",
        "val": [
          0.14332069054406746,
          0.001
        ],
        "n": 1
      },
      {
        "feature": "fast_AHP",
        "val": [
          11.754323710343467,
          0.001
        ],
        "n": 1
      },
      {
        "feature": "adaptation_index2",
        "val": [
          0.008296929415215244,
          0.001
        ],
        "n": 1
      },
      {
        "feature": "AHP_slow_time",
        "val": [
          0.2539448722540889,
          0.001
        ],
        "n": 1
      },
      {
        "feature": "doublet_ISI",
        "val": [
          6.400000000023283,
          0.001
        ],
        "n": 1
      },
      {
        "feature": "decay_time_constant_after_stim",
        "val": [
          92.58323122939679,
          0.001
        ],
        "n": 1
      },
      {
        "feature": "mean_AP_amplitude",
        "val": [
          54.46043986068541,
          0.001
        ],
        "n": 1
      }
    ]
  }
}