{
  "step_80": {
    "soma": [
      {
        "feature": "voltage_base",
        "val": [
          -83.35434416961708,
          0.14965666246944578
        ],
        "n": 3
      },
      {
        "feature": "inv_time_to_first_spike",
        "val": [
          0.0,
          0.001
        ],
        "n": 3
      },
      {
        "feature": "inv_first_ISI",
        "val": [
          0.0,
          0.001
        ],
        "n": 3
      },
      {
        "feature": "inv_second_ISI",
        "val": [
          0.0,
          0.001
        ],
        "n": 3
      },
      {
        "feature": "inv_third_ISI",
        "val": [
          0.0,
          0.001
        ],
        "n": 3
      },
      {
        "feature": "inv_fourth_ISI",
        "val": [
          0.0,
          0.001
        ],
        "n": 3
      },
      {
        "feature": "inv_fifth_ISI",
        "val": [
          0.0,
          0.001
        ],
        "n": 3
      },
      {
        "feature": "decay_time_constant_after_stim",
        "val": [
          1475.1726728923359,
          1256.2361588511453
        ],
        "n": 3
      }
    ]
  },
  "step_100": {
    "soma": [
      {
        "feature": "AHP_depth",
        "val": [
          8.07836194940071,
          0.7043909321992741
        ],
        "n": 6
      },
      {
        "feature": "AP1_amp",
        "val": [
          57.27604531087039,
          1.7258780684913064
        ],
        "n": 6
      },
      {
        "feature": "AP2_amp",
        "val": [
          62.15430019888902,
          2.557556360600702
        ],
        "n": 4
      },
      {
        "feature": "AHP_time_from_peak",
        "val": [
          0.9000000000032742,
          0.001
        ],
        "n": 6
      },
      {
        "feature": "AP_amplitude",
        "val": [
          58.25070822240793,
          2.226872483155936
        ],
        "n": 6
      },
      {
        "feature": "AP_duration_half_width",
        "val": [
          0.3831597222236162,
          0.014687335827872433
        ],
        "n": 6
      },
      {
        "feature": "AP_begin_width",
        "val": [
          0.7895833333362058,
          0.031800703171936
        ],
        "n": 6
      },
      {
        "feature": "mean_frequency",
        "val": [
          11.253659934383515,
          3.8366512214579407
        ],
        "n": 6
      },
      {
        "feature": "burst_number",
        "val": [
          1.0,
          0.001
        ],
        "n": 1
      },
      {
        "feature": "voltage_base",
        "val": [
          -83.99214812850956,
          0.4841076061494836
        ],
        "n": 11
      },
      {
        "feature": "inv_time_to_first_spike",
        "val": [
          5.387844989356757,
          5.412177149660511
        ],
        "n": 11
      },
      {
        "feature": "inv_first_ISI",
        "val": [
          10.053990963695375,
          17.271432144805907
        ],
        "n": 11
      },
      {
        "feature": "inv_second_ISI",
        "val": [
          6.2314489657903485,
          13.26628944093
        ],
        "n": 11
      },
      {
        "feature": "inv_third_ISI",
        "val": [
          2.7800945232036756,
          8.791430803883443
        ],
        "n": 11
      },
      {
        "feature": "inv_fourth_ISI",
        "val": [
          2.689618074223674,
          8.505319150502624
        ],
        "n": 11
      },
      {
        "feature": "inv_fifth_ISI",
        "val": [
          3.4048348654966363,
          10.76703323172242
        ],
        "n": 11
      },
      {
        "feature": "APlast_amp",
        "val": [
          58.773440483853925,
          4.304773153100676
        ],
        "n": 6
      },
      {
        "feature": "AP_begin_voltage",
        "val": [
          -49.140029907368536,
          1.1330100065319242
        ],
        "n": 6
      },
      {
        "feature": "ISI_CV",
        "val": [
          1.1700017567357628,
          0.001
        ],
        "n": 1
      },
      {
        "feature": "ISI_log_slope",
        "val": [
          1.0008065002817776,
          0.001
        ],
        "n": 1
      },
      {
        "feature": "fast_AHP",
        "val": [
          26.45130979697683,
          0.811441522811118
        ],
        "n": 4
      },
      {
        "feature": "adaptation_index2",
        "val": [
          0.20519988943465223,
          0.001
        ],
        "n": 1
      },
      {
        "feature": "AHP_slow_time",
        "val": [
          0.1423542695478685,
          0.01903813551542262
        ],
        "n": 2
      },
      {
        "feature": "doublet_ISI",
        "val": [
          61.250000000222826,
          38.817811633462334
        ],
        "n": 4
      },
      {
        "feature": "decay_time_constant_after_stim",
        "val": [
          1356.446828104594,
          1465.22683193856
        ],
        "n": 11
      },
      {
        "feature": "mean_AP_amplitude",
        "val": [
          58.25070822240793,
          2.226872483155936
        ],
        "n": 6
      }
    ]
  },
  "step_125": {
    "soma": [
      {
        "feature": "AHP_depth",
        "val": [
          8.5790154758221,
          0.3490815036454605
        ],
        "n": 12
      },
      {
        "feature": "AP1_amp",
        "val": [
          57.02409184381403,
          2.1367147397532964
        ],
        "n": 12
      },
      {
        "feature": "AP2_amp",
        "val": [
          62.25694843708628,
          1.868885999426576
        ],
        "n": 9
      },
      {
        "feature": "AHP_time_from_peak",
        "val": [
          0.9160929951724147,
          0.019037236804680526
        ],
        "n": 12
      },
      {
        "feature": "AP_amplitude",
        "val": [
          57.58731041050162,
          1.7233028311687233
        ],
        "n": 12
      },
      {
        "feature": "AP_duration_half_width",
        "val": [
          0.369631894123728,
          0.04089141840064534
        ],
        "n": 12
      },
      {
        "feature": "AP_begin_width",
        "val": [
          0.7878723832556842,
          0.02477283263087557
        ],
        "n": 12
      },
      {
        "feature": "mean_frequency",
        "val": [
          14.523641108894237,
          6.696553612983118
        ],
        "n": 12
      },
      {
        "feature": "burst_number",
        "val": [
          1.6666666666666667,
          0.9428090415820634
        ],
        "n": 3
      },
      {
        "feature": "voltage_base",
        "val": [
          -84.1235164661409,
          0.3682436858599681
        ],
        "n": 18
      },
      {
        "feature": "inv_time_to_first_spike",
        "val": [
          9.178672050747531,
          7.566593048892868
        ],
        "n": 18
      },
      {
        "feature": "inv_first_ISI",
        "val": [
          24.548622350096096,
          27.088443833817927
        ],
        "n": 18
      },
      {
        "feature": "inv_second_ISI",
        "val": [
          10.28785681580473,
          19.124969440301165
        ],
        "n": 18
      },
      {
        "feature": "inv_third_ISI",
        "val": [
          6.705239814324266,
          14.596505437600849
        ],
        "n": 18
      },
      {
        "feature": "inv_fourth_ISI",
        "val": [
          6.521485665456442,
          16.18689856211547
        ],
        "n": 18
      },
      {
        "feature": "inv_fifth_ISI",
        "val": [
          4.549925526747179,
          11.607661124668184
        ],
        "n": 18
      },
      {
        "feature": "APlast_amp",
        "val": [
          56.2623722672144,
          4.657327725123791
        ],
        "n": 12
      },
      {
        "feature": "AP_begin_voltage",
        "val": [
          -48.84585838932146,
          1.0478400958734762
        ],
        "n": 12
      },
      {
        "feature": "ISI_CV",
        "val": [
          1.4043402710370803,
          0.2711618868697348
        ],
        "n": 4
      },
      {
        "feature": "ISI_log_slope",
        "val": [
          1.3469401523886562,
          1.0436163488337378
        ],
        "n": 4
      },
      {
        "feature": "fast_AHP",
        "val": [
          26.602077315609097,
          0.6189999638389716
        ],
        "n": 9
      },
      {
        "feature": "adaptation_index2",
        "val": [
          0.30614545520044173,
          0.2870731061208727
        ],
        "n": 4
      },
      {
        "feature": "AHP_slow_time",
        "val": [
          0.11763799872653839,
          0.05556511103508945
        ],
        "n": 5
      },
      {
        "feature": "doublet_ISI",
        "val": [
          28.433333333436774,
          26.788388861277177
        ],
        "n": 9
      },
      {
        "feature": "decay_time_constant_after_stim",
        "val": [
          1010.058500940023,
          1105.2800208350936
        ],
        "n": 18
      },
      {
        "feature": "mean_AP_amplitude",
        "val": [
          57.58731041050162,
          1.7233028311687233
        ],
        "n": 12
      }
    ]
  },
  "step_150": {
    "soma": [
      {
        "feature": "AHP_depth",
        "val": [
          9.087025452199526,
          0.4040806804746319
        ],
        "n": 11
      },
      {
        "feature": "AP1_amp",
        "val": [
          62.51420776254615,
          6.011073291027265
        ],
        "n": 11
      },
      {
        "feature": "AP2_amp",
        "val": [
          58.8622194152513,
          3.3126259355128145
        ],
        "n": 11
      },
      {
        "feature": "AHP_time_from_peak",
        "val": [
          0.9283853355725072,
          0.017540606348357392
        ],
        "n": 11
      },
      {
        "feature": "AP_amplitude",
        "val": [
          56.70101207659052,
          1.1897460000732185
        ],
        "n": 11
      },
      {
        "feature": "AP_duration_half_width",
        "val": [
          0.35964451830689387,
          0.039619965127290026
        ],
        "n": 11
      },
      {
        "feature": "AP_begin_width",
        "val": [
          0.7942171717200611,
          0.015978905940141282
        ],
        "n": 11
      },
      {
        "feature": "mean_frequency",
        "val": [
          26.208553617638938,
          12.986984851721976
        ],
        "n": 11
      },
      {
        "feature": "burst_number",
        "val": [
          2.0,
          0.5345224838248488
        ],
        "n": 7
      },
      {
        "feature": "voltage_base",
        "val": [
          -83.83487893624721,
          0.2922008638797306
        ],
        "n": 11
      },
      {
        "feature": "inv_time_to_first_spike",
        "val": [
          26.167445065176878,
          7.933948432465036
        ],
        "n": 11
      },
      {
        "feature": "inv_first_ISI",
        "val": [
          51.13173339035004,
          10.249015184832269
        ],
        "n": 11
      },
      {
        "feature": "inv_second_ISI",
        "val": [
          48.370076919220175,
          31.23790910790313
        ],
        "n": 11
      },
      {
        "feature": "inv_third_ISI",
        "val": [
          40.43690662680241,
          31.625845185514375
        ],
        "n": 11
      },
      {
        "feature": "inv_fourth_ISI",
        "val": [
          42.95808262615898,
          33.13242375237815
        ],
        "n": 11
      },
      {
        "feature": "inv_fifth_ISI",
        "val": [
          36.44254527336752,
          32.31946456079775
        ],
        "n": 11
      },
      {
        "feature": "APlast_amp",
        "val": [
          54.0383546594449,
          4.123910769203028
        ],
        "n": 11
      },
      {
        "feature": "AP_begin_voltage",
        "val": [
          -48.378576916681666,
          0.6892183794465376
        ],
        "n": 11
      },
      {
        "feature": "ISI_CV",
        "val": [
          1.6734356755858268,
          0.9958198167025638
        ],
        "n": 8
      },
      {
        "feature": "ISI_log_slope",
        "val": [
          0.6228510433120199,
          0.9054289790183742
        ],
        "n": 8
      },
      {
        "feature": "fast_AHP",
        "val": [
          26.450667066549737,
          0.4683871627854883
        ],
        "n": 11
      },
      {
        "feature": "adaptation_index2",
        "val": [
          0.10404362306440683,
          0.2547338203234301
        ],
        "n": 8
      },
      {
        "feature": "AHP_slow_time",
        "val": [
          0.20909742663130132,
          0.08319542474112018
        ],
        "n": 9
      },
      {
        "feature": "doublet_ISI",
        "val": [
          20.363636363710444,
          4.116766764727465
        ],
        "n": 11
      },
      {
        "feature": "decay_time_constant_after_stim",
        "val": [
          347.23206708012555,
          442.7280382958564
        ],
        "n": 11
      },
      {
        "feature": "mean_AP_amplitude",
        "val": [
          56.70101207659052,
          1.1897460000732187
        ],
        "n": 11
      }
    ]
  },
  "step_175": {
    "soma": [
      {
        "feature": "AHP_depth",
        "val": [
          9.74776803979802,
          0.5106795181216907
        ],
        "n": 9
      },
      {
        "feature": "AP1_amp",
        "val": [
          74.19965593599552,
          12.098220042200705
        ],
        "n": 9
      },
      {
        "feature": "AP2_amp",
        "val": [
          59.387156010192065,
          5.527717381437917
        ],
        "n": 9
      },
      {
        "feature": "AHP_time_from_peak",
        "val": [
          0.9316113207261763,
          0.01707875866354491
        ],
        "n": 9
      },
      {
        "feature": "AP_amplitude",
        "val": [
          56.43251427533612,
          0.9869200812319099
        ],
        "n": 9
      },
      {
        "feature": "AP_duration_half_width",
        "val": [
          0.3661876622254394,
          0.011181419074641003
        ],
        "n": 9
      },
      {
        "feature": "AP_begin_width",
        "val": [
          0.831272566145741,
          0.041331073441479974
        ],
        "n": 9
      },
      {
        "feature": "mean_frequency",
        "val": [
          46.2255755372341,
          22.548772306707093
        ],
        "n": 9
      },
      {
        "feature": "burst_number",
        "val": [
          1.4444444444444444,
          0.4969039949999533
        ],
        "n": 9
      },
      {
        "feature": "voltage_base",
        "val": [
          -83.83639000288537,
          0.36444137025287987
        ],
        "n": 9
      },
      {
        "feature": "inv_time_to_first_spike",
        "val": [
          34.799899783224376,
          3.53274825497046
        ],
        "n": 9
      },
      {
        "feature": "inv_first_ISI",
        "val": [
          75.21457101914584,
          34.46879088943214
        ],
        "n": 9
      },
      {
        "feature": "inv_second_ISI",
        "val": [
          82.88806022072899,
          20.83454122406834
        ],
        "n": 9
      },
      {
        "feature": "inv_third_ISI",
        "val": [
          76.51466798929317,
          20.74098141429047
        ],
        "n": 9
      },
      {
        "feature": "inv_fourth_ISI",
        "val": [
          79.07237095412472,
          14.086017569151497
        ],
        "n": 9
      },
      {
        "feature": "inv_fifth_ISI",
        "val": [
          77.40567514715804,
          13.896716111992001
        ],
        "n": 9
      },
      {
        "feature": "APlast_amp",
        "val": [
          53.34722445507819,
          2.0896498979252573
        ],
        "n": 9
      },
      {
        "feature": "AP_begin_voltage",
        "val": [
          -48.49279728390172,
          0.540295118710094
        ],
        "n": 9
      },
      {
        "feature": "ISI_CV",
        "val": [
          1.2204552916002025,
          1.203644702325418
        ],
        "n": 9
      },
      {
        "feature": "ISI_log_slope",
        "val": [
          0.24977956568558504,
          0.11872265613912263
        ],
        "n": 9
      },
      {
        "feature": "fast_AHP",
        "val": [
          25.545919432986857,
          0.783303799614861
        ],
        "n": 9
      },
      {
        "feature": "adaptation_index2",
        "val": [
          0.006297844465865093,
          0.003580220111045717
        ],
        "n": 9
      },
      {
        "feature": "AHP_slow_time",
        "val": [
          0.3025590039077581,
          0.04870649244445868
        ],
        "n": 9
      },
      {
        "feature": "doublet_ISI",
        "val": [
          16.288888888948147,
          7.031586583190379
        ],
        "n": 9
      },
      {
        "feature": "decay_time_constant_after_stim",
        "val": [
          235.68615390783629,
          484.37751381578863
        ],
        "n": 9
      },
      {
        "feature": "mean_AP_amplitude",
        "val": [
          56.43251427533612,
          0.986920081231913
        ],
        "n": 9
      }
    ]
  },
  "step_200": {
    "soma": [
      {
        "feature": "AHP_depth",
        "val": [
          10.170912098222542,
          0.09780079858165455
        ],
        "n": 3
      },
      {
        "feature": "AP1_amp",
        "val": [
          87.09896138475784,
          12.958417286508626
        ],
        "n": 3
      },
      {
        "feature": "AP2_amp",
        "val": [
          61.85937843381575,
          5.5001938961455545
        ],
        "n": 3
      },
      {
        "feature": "AHP_time_from_peak",
        "val": [
          0.9312909753678928,
          0.024995070444039424
        ],
        "n": 3
      },
      {
        "feature": "AP_amplitude",
        "val": [
          56.554512377559654,
          1.323694775412004
        ],
        "n": 3
      },
      {
        "feature": "AP_duration_half_width",
        "val": [
          0.366183132228582,
          0.0094808932207824
        ],
        "n": 3
      },
      {
        "feature": "AP_begin_width",
        "val": [
          0.8817887129241123,
          0.03398745507477008
        ],
        "n": 3
      },
      {
        "feature": "mean_frequency",
        "val": [
          69.77605298645135,
          4.269973695994974
        ],
        "n": 3
      },
      {
        "feature": "burst_number",
        "val": [
          1.0,
          0.001
        ],
        "n": 3
      },
      {
        "feature": "voltage_base",
        "val": [
          -83.73325451055992,
          0.05535779087847676
        ],
        "n": 3
      },
      {
        "feature": "inv_time_to_first_spike",
        "val": [
          37.79291492160526,
          0.6026131266638528
        ],
        "n": 3
      },
      {
        "feature": "inv_first_ISI",
        "val": [
          106.49585921286308,
          28.785131060949226
        ],
        "n": 3
      },
      {
        "feature": "inv_second_ISI",
        "val": [
          110.40613207002735,
          7.625088125340446
        ],
        "n": 3
      },
      {
        "feature": "inv_third_ISI",
        "val": [
          89.2688934652512,
          23.639693866123025
        ],
        "n": 3
      },
      {
        "feature": "inv_fourth_ISI",
        "val": [
          94.80990424352159,
          4.059347418373999
        ],
        "n": 3
      },
      {
        "feature": "inv_fifth_ISI",
        "val": [
          93.41484098753638,
          7.060741853394123
        ],
        "n": 3
      },
      {
        "feature": "APlast_amp",
        "val": [
          53.927085323673545,
          2.2339318387445495
        ],
        "n": 3
      },
      {
        "feature": "AP_begin_voltage",
        "val": [
          -48.88824552864593,
          0.6608795472015241
        ],
        "n": 3
      },
      {
        "feature": "ISI_CV",
        "val": [
          0.15613085250633882,
          0.01015985539839653
        ],
        "n": 3
      },
      {
        "feature": "ISI_log_slope",
        "val": [
          0.15256845964635313,
          0.010048310770951467
        ],
        "n": 3
      },
      {
        "feature": "fast_AHP",
        "val": [
          24.644129166011112,
          0.6972832328431806
        ],
        "n": 3
      },
      {
        "feature": "adaptation_index2",
        "val": [
          0.004106664711641058,
          0.0004578595580200495
        ],
        "n": 3
      },
      {
        "feature": "AHP_slow_time",
        "val": [
          0.3611496081427554,
          0.02123469094769604
        ],
        "n": 3
      },
      {
        "feature": "doublet_ISI",
        "val": [
          10.133333333370198,
          2.8015868519369516
        ],
        "n": 3
      },
      {
        "feature": "decay_time_constant_after_stim",
        "val": [
          26.454190009437383,
          8.651376670624693
        ],
        "n": 3
      },
      {
        "feature": "mean_AP_amplitude",
        "val": [
          56.55451237755966,
          1.3236947754120096
        ],
        "n": 3
      }
    ]
  }
}